winloop/loop.cp39-win_amd64.pyd
winloop.loop-0.0.1.dist-info/LICENSE-APACHE
winloop.loop-0.0.1.dist-info/LICENSE-MIT
winloop.loop-0.0.1.dist-info/METADATA
winloop.loop-0.0.1.dist-info/WHEEL
winloop.loop-0.0.1.dist-info/top_level.txt
winloop.loop-0.0.1.dist-info/RECORD
