Metadata-Version: 2.1
Name: winloop.loop
Version: 0.0.1
Summary: An Alternative library for uvloop compatability with windows
Author: Vizonex
License: MIT
Keywords: winloop,libuv,windows,cython,fast-asyncio,uvloop-alternative
Platform: Microsoft Windows
Classifier: Programming Language :: Python :: 3.9
Classifier: Programming Language :: Python :: 3.10
Classifier: Programming Language :: Python :: 3.11
Classifier: Intended Audience :: Developers
Classifier: Framework :: AsyncIO
License-File: LICENSE-APACHE
License-File: LICENSE-MIT
